CalC.v
`timescale 1ns / 1ns

module CalC(input [15:0]x, 
            input [15:0]y,
            input zx,nx,zy,ny,f,no,
            output reg ng,zr,
            output reg [15:0]o);
            
            wire [15:0]x1;
            wire [15:0]y1;
            wire [16:0]f1;
            wire [16:0]f2;
            assign x1 = ~x&{16{nx}}|{16{nx&zx}}|{16{~nx&~zx}}&x;
            assign y1 = ~y&{16{ny}}|{16{ny&zy}}|{16{~ny&~zy}}&y;
            assign f1[16:0] =f?(x1+y1):(x1&y1);
            assign f2[16:0] =no?~f1:f1;

            always @(*) begin
                ng <= f2[16];
                zr <= (f2=={16{1'b0}});           
                o <= f2[15:0];
            end
endmodule

Processor.v
//Some changes were made from the given Ichip PS, so that it could be pipelined
//x input is given from the Acc, and y input is given by the user as address(present in instruction)

`timescale 1ns/1ns
`include "CalC.v"

// only implement the IF stage for 0 output
module pipeAcc16(
    clk1, clk2, rst
);

input clk1, clk2, rst;

// Memory
parameter l_ins = 401, l_tot = 1024;
reg [15:0] ins_mem[l_ins-1:0];
reg [15:0] data_mem[l_tot-l_ins-1:0];
reg [5:0] cb_ID, cb_EX;

// IF stage registers
reg [15:0] PC, IF_ID_IR;

// ID stage registers
reg [15:0]  ID_EX_IR, ID_EX_A;

// EX stage registers
reg [15:0]  EX_MEM_IR;     //output reg since ALU is completely a combinational device in our design
reg [15:0]  Acc;
wire [15:0] EX_MEM_ALUOut;

// Mem registers
reg [9:0]EX_MEM_Add;

// halt flag
reg HLT, TAKEN_BRANCH, Wrt;
// cond = MSB - ng, LSB - zr
wire [1:0]cond;

// give those control bits to CalC.v and take outputs at clk1
CalC func (.x(Acc), .y(ID_EX_A), .zx(cb_ID[5]),
            .nx(cb_ID[4]), .zy(cb_ID[3]), .ny(cb_ID[2]),
            .f(cb_ID[1]), .no(cb_ID[0]), .ng(cond[1]),
            .zr(cond[0]), .o(EX_MEM_ALUOut));

// very simple IF stage
always @(posedge clk1) begin

    if(~HLT && ~TAKEN_BRANCH){
        IF_ID_IR    <=  ins_mem[PC];
        //NPC specially stores sequential ins
        NPC         <= PC+1;
    }   
    PC  <=  TAKEN_BRANCH ?  (ID_EX_IR[15] ? ins_mem[ins_mem[ID_EX_IR[9:0]]] : ins_mem[ID_EX_IR[9:0]]) :  NPC;
    if(TAKEN_BRANCH) TAKEN_BRANCH   <= 0;
end

// very simple ID stage
always @(posedge clk2) begin

    if(~HLT)begin
        ID_EX_IR                           <=  IF_ID_IR;

        //always prefetch the operands
        if(~ID_EX_IR[15])       ID_EX_A    <=  data_mem[ID_EX_IR[9:0]];             //direct mem access

        else                    ID_EX_A    <=  data_mem[data_mem[ID_EX_IR[9:0]]];   //indirect mem access


        //opcode assignment
        case (IF_ID_IR[14:10])
            5'b00000:   cb_ID  <=  6'b101010;
            5'b00001:   cb_ID  <=  6'b111111;
            5'b00010:   cb_ID  <=  6'b111010;
            5'b00011:   cb_ID  <=  6'b001100;
            5'b00100:   cb_ID  <=  6'b110000;
            5'b00101:   cb_ID  <=  6'b001101;
            5'b00110:   cb_ID  <=  6'b110001;
            5'b00111:   cb_ID  <=  6'b001111;
            5'b01000:   cb_ID  <=  6'b110011;
            5'b01001:   cb_ID  <=  6'b011111;
            5'b01010:   cb_ID  <=  6'b110111;
            5'b01011:   cb_ID  <=  6'b001110;
            5'b01100:   cb_ID  <=  6'b110010;
            5'b01101:   cb_ID  <=  6'b000010;
            5'b01110:   cb_ID  <=  6'b010011;
            5'b01111:   cb_ID  <=  6'b000111;
            5'b10000:   cb_ID  <=  6'b000000;
            5'b10001:   cb_ID  <=  6'b010101;
            5'b10010:   cb_ID  <=  6'b110000;
            5'b10011:   Wrt    <=  1;
            5'b10100:   TAKEN_BRANCH    <= 1;
            5'b10101:   TAKEN_BRANCH    <= cond[0];
            5'b10110:   TAKEN_BRANCH    <= cond[1];
            5'b10111:   HLT             <= 1;
            default:    cb_ID  <=  6'b110000;
        endcase
    end
end

// very simple EX stage
always @(posedge clk1) begin
    if(~HLT)begin
        // EX_MEM_IR   <=  IF_ID_IR; no need to do this
        cb_EX       <=  cb_ID;
        /* since inputs are being given at clock edge output will also appear at clock edge
            there is no special need to initialize it as a wire and latch it onto a reg at
            clock edge.
        */
        //  if Wrt ins, then take the store address from the instrn
        if(Wrt) EX_MEM_Add  <= (ID_EX_IR[15] ? data_mem[data_mem[ID_EX_IR[9:0]]] : data_mem[ID_EX_IR[9:0]]);
    end
end

// Acc Stage
always @(posedge clk2) begin
    if(~HLT) begin
        //write the final output to Acc
        Acc  <=  EX_MEM_ALUOut;
        //if Wrt, then store the data in the given add
        if(Wrt) data_mem[EX_MEM_Add]   <= Acc;
    end
end
    
endmodule

testbench.v
`include "Processor.v"

module tb_Processor;
reg clk1, clk2;
integer fd, i;

pipeAcc16 dut
(
    .clk1 (clk1),
    .clk2 (clk2)
);

localparam CLK_PERIOD = 2;
always #(CLK_PERIOD/2) begin
    clk1 <= ~clk1;
    #1 clk2 <= ~clk2;
end

// clock initializations
initial begin
    clk1 <= 0;
    clk2 <= 0;
    #20 $finish;
end

// initialization of PC, other flags
initial begin
    dut.pipeAcc16.HLT      <= 0;
    dut.pipeAcc16.Wrt      <=  0;
    dut.pipeAcc16.TAKEN_BRANCH  <= 0;
    // dut.pipeAcc16.TAKEN_BRANCH <= 0;
    dut.pipeAcc16.EX_MEM_IR    <= {16{1'b0}};
    dut.pipeAcc16.PC           <= {16{1'b0}};

end

// initialization of Memory and Reg bank
initial begin
    dut.ins_mem[0]  <= 16'h5006;
    dut.ins_mem[1]  <= 16'hB401;
    dut.ins_mem[6]  <= 16'h2800;
    dut.data_mem[0] <= 16'h0000;
    dut.data_mem[1] <= 16'h0002;
    dut.data_mem[2] <= 16'h0003;
    
    $dumpfile("op.vcd");
    $dumpvars(0,tb_Processor);
end

endmodule

op.vcd
$date
	Thu May 18 02:21:27 2023
$end
$version
	Icarus Verilog
$end
$timescale
	1ns
$end
$scope module tb_Processor $end
$var reg 1 ! clk1 $end
$var reg 1 " clk2 $end
$scope module dut $end
$var wire 1 ! clk1 $end
$var wire 1 " clk2 $end
$var wire 1 # rst $end
$var wire 2 $ cond [1:0] $end
$var wire 16 % EX_MEM_ALUOut [15:0] $end
$var reg 16 & Acc [15:0] $end
$var reg 10 ' EX_MEM_Add [9:0] $end
$var reg 16 ( EX_MEM_IR [15:0] $end
$var reg 1 ) HLT $end
$var reg 16 * ID_EX_A [15:0] $end
$var reg 16 + ID_EX_IR [15:0] $end
$var reg 16 , IF_ID_IR [15:0] $end
$var reg 16 - PC [15:0] $end
$var reg 1 . TAKEN_BRANCH $end
$var reg 1 / Wrt $end
$var reg 6 0 cb_EX [5:0] $end
$var reg 6 1 cb_ID [5:0] $end
$scope module func $end
$var wire 1 2 f $end
$var wire 1 3 no $end
$var wire 1 4 nx $end
$var wire 1 5 ny $end
$var wire 16 6 x [15:0] $end
$var wire 16 7 x1 [15:0] $end
$var wire 16 8 y [15:0] $end
$var wire 16 9 y1 [15:0] $end
$var wire 1 : zx $end
$var wire 1 ; zy $end
$var wire 17 < f2 [16:0] $end
$var wire 17 = f1 [16:0] $end
$var reg 1 > ng $end
$var reg 16 ? o [15:0] $end
$var reg 1 @ zr $end
$upscope $end
$upscope $end
$upscope $end
$enddefinitions $end
#0
$dumpvars
x@
bx ?
x>
bx =
bx <
x;
x:
bx 9
bx 8
bx 7
bx 6
x5
x4
x3
x2
bx 1
bx 0
0/
0.
b0 -
bx ,
bx +
bx *
0)
b0 (
bx '
bx &
bx %
bx $
z#
0"
0!
$end
#1
b1 -
b101000000000110 ,
1!
#2
1.
b101000000000110 +
1"
#3
0!
#4
0"
#5
0.
b10100000000000 -
1!
#6
1.
1"
#7
0!
#8
0"
#9
0.
1!
#10
1.
1"
#11
0!
#12
0"
#13
0.
1!
#14
1.
1"
#15
0!
#16
0"
#17
0.
1!
#18
1.
1"
