CalC.v
`timescale 1ns / 1ns

module CalC(input [15:0]x, 
            input [15:0]y,
            input zx,nx,zy,ny,f,no,
            output reg ng,zr,
            output reg [15:0]o);
            
            wire [15:0]x1;
            wire [15:0]y1;
            wire [16:0]f1;
            wire [16:0]f2;
            assign x1 = ~x&{16{nx}}|{16{nx&zx}}|{16{~nx&~zx}}&x;
            assign y1 = ~y&{16{ny}}|{16{ny&zy}}|{16{~ny&~zy}}&y;
            assign f1[16:0] =f?(x1+y1):(x1&y1);
            assign f2[16:0] =no?~f1:f1;

            always @(*) begin
                ng <= f2[16];
                zr <= (f2=={16{1'b0}});           
                o <= f2[15:0];
            end
endmodule

Processor.v
`timescale 1ns/1ns
`include "CalC.v"

// only implement the IF stage for 0 output
module pipeAcc16(
    clk1, clk2, rst
);

input clk1, clk2, rst;

// Memory
parameter l_ins = 401, l_tot = 1024;
reg [15:0] ins_mem[l_ins-1:0];
reg [15:0] data_mem[l_tot-l_ins-1:0];
reg [5:0] cb_ID, cb_EX;

// IF stage registers
reg [15:0] PC, IF_ID_IR;

// ID stage registers
reg [15:0]  ID_EX_IR, ID_EX_A;

// EX stage registers
reg [15:0]  EX_MEM_IR;     //output reg since ALU is completely a combinational device in our design
reg [15:0]  Acc;
wire [15:0] EX_MEM_ALUOut;

// Mem parameters
integer data_ptr;

// halt flag
reg HLT;
// cond = MSB - ng, LSB - zr
wire [1:0]cond;

// give those control bits to CalC.v and take outputs at clk1
CalC func (.x(Acc), .y(ID_EX_A), .zx(cb_EX[5]),
            .nx(cb_EX[4]), .zy(cb_EX[3]), .ny(cb_EX[2]),
            .f(cb_EX[1]), .no(cb_EX[0]), .ng(cond[1]),
            .zr(cond[0]), .o(EX_MEM_ALUOut));

// very simple IF stage
always @(posedge clk1) begin

    data_ptr        <=  data_ptr+1;
    if(~HLT) begin
        IF_ID_IR    <=  ins_mem[PC];
        // if(ID_EX_type == BRANCH)
        // PC          <=  
        PC          <=  PC+1;
    end    
end

// very simple ID stage
always @(posedge clk2) begin

    if(~HLT)begin
        ID_EX_IR   <=  IF_ID_IR;

        if(~ID_EX_IR)   ID_EX_A    <=  data_mem[ID_EX_IR[9:0]];             //direct mem access

        else            ID_EX_A    <=  data_mem[data_mem[ID_EX_IR[9:0]]];   //indirect mem access

        case (ID_EX_IR[14:10])
            5'b00000:   cb_ID  <=  6'b101010;
            5'b00001:   cb_ID  <=  6'b111111;
            5'b00010:   cb_ID  <=  6'b111010;
            5'b00011:   cb_ID  <=  6'b001100;
            5'b00100:   cb_ID  <=  6'b110000;
            5'b00101:   cb_ID  <=  6'b001101;
            5'b00110:   cb_ID  <=  6'b110001;
            5'b00111:   cb_ID  <=  6'b001111;
            5'b01000:   cb_ID  <=  6'b110011;
            5'b01001:   cb_ID  <=  6'b011111;
            5'b01010:   cb_ID  <=  6'b110111;
            5'b01011:   cb_ID  <=  6'b001110;
            5'b01100:   cb_ID  <=  6'b110010;
            default:    cb_ID  <=  6'b110000;
        endcase
    end
end

// very simple EX stage
always @(posedge clk1) begin
    if(~HLT)begin
        cb_EX       <=  cb_ID;
        EX_MEM_IR   <=  ID_EX_IR;
        /* since inpurs are being given at clock edge output will also appear at clock edge
            there is no special need to initialize it as a wire and latch it onto a reg at
            clock edge.
        */
    end
end

// Mem Stage
always @(posedge clk2) begin
    Acc  <=  EX_MEM_ALUOut;
    
end
    
endmodule

testbench.v
`include "Processor.v"

module tb_Processor;
reg clk1, clk2;
integer fd, i;

pipeAcc16 dut
(
    .clk1 (clk1),
    .clk2 (clk2)
);

localparam CLK_PERIOD = 2;
always #(CLK_PERIOD/2) begin
    clk1 <= ~clk1;
    #1 clk2 <= ~clk2;
end

// clock initializations
initial begin
    clk1 <= 0;
    clk2 <= 0;
    #20 $finish;
end

// initialization of PC, other flags
initial begin
    dut.pipeAcc16.HLT      <= 0;
    dut.pipeAcc16.data_ptr <= -1;
    // dut.pipeAcc16.TAKEN_BRANCH <= 0;
    dut.pipeAcc16.EX_MEM_IR    <= {16{1'b0}};
    dut.pipeAcc16.PC           <= {16{1'b0}};

end

// initialization of Memory and Reg bank
initial begin
    dut.ins_mem[0]  <= 16'h2800;
    dut.ins_mem[1]  <= 16'hB401;
    dut.data_mem[0] <= 16'h0000;
    dut.data_mem[1] <= 16'h0002;
    dut.data_mem[2] <= 16'h0003;

    fd = $fopen("tst.txt", "w");
    // $fstrobe(fd, $time, dut.pipeAcc16.Reg[1]);
    $fstrobe(fd, $time, dut.pipeAcc16.Acc);
    
    $dumpfile("op.vcd");
    $dumpvars(0,tb_Processor);
end

endmodule

op.vcd
$date
	Tue May 16 02:15:32 2023
$end
$version
	Icarus Verilog
$end
$timescale
	1ns
$end
$scope module tb_Processor $end
$var reg 1 ! clk1 $end
$var reg 1 " clk2 $end
$var integer 32 # fd [31:0] $end
$scope module dut $end
$var wire 1 ! clk1 $end
$var wire 1 " clk2 $end
$var wire 1 $ rst $end
$var wire 2 % cond [1:0] $end
$var wire 16 & EX_MEM_ALUOut [15:0] $end
$var reg 16 ' Acc [15:0] $end
$var reg 16 ( EX_MEM_IR [15:0] $end
$var reg 1 ) HLT $end
$var reg 16 * ID_EX_A [15:0] $end
$var reg 16 + ID_EX_IR [15:0] $end
$var reg 16 , IF_ID_IR [15:0] $end
$var reg 16 - PC [15:0] $end
$var reg 6 . cb_EX [5:0] $end
$var reg 6 / cb_ID [5:0] $end
$var integer 32 0 data_ptr [31:0] $end
$scope module func $end
$var wire 1 1 f $end
$var wire 1 2 no $end
$var wire 1 3 nx $end
$var wire 1 4 ny $end
$var wire 16 5 x [15:0] $end
$var wire 16 6 x1 [15:0] $end
$var wire 16 7 y [15:0] $end
$var wire 16 8 y1 [15:0] $end
$var wire 1 9 zx $end
$var wire 1 : zy $end
$var wire 17 ; f2 [16:0] $end
$var wire 17 < f1 [16:0] $end
$var reg 1 = ng $end
$var reg 16 > o [15:0] $end
$var reg 1 ? zr $end
$upscope $end
$upscope $end
$upscope $end
$enddefinitions $end
#0
$dumpvars
x?
bx >
x=
bx <
bx ;
x:
x9
bx 8
bx 7
bx 6
bx 5
x4
x3
x2
x1
b11111111111111111111111111111111 0
bx /
bx .
b0 -
bx ,
bx +
bx *
0)
b0 (
bx '
bx &
bx %
z$
b10000000000000000000000000000011 #
0"
0!
$end
#1
b1 -
b10100000000000 ,
b0 0
bx (
1!
#2
b110000 /
b10100000000000 +
1"
#3
0!
#4
0"
#5
b0x %
0=
b1111111111111111 6
b0xxxxxxxxxxxxxxxx ;
b0xxxxxxxxxxxxxxxx <
19
13
0:
04
01
02
b10100000000000 (
b110000 .
b10 -
b1011010000000001 ,
b1 0
1!
#6
b0 &
b0 >
b1 %
1?
b0 ;
b0 <
b0 8
b110111 /
b0 *
b0 7
b1011010000000001 +
1"
#7
0!
#8
0"
#9
b1 &
b1 >
0?
b0 %
0=
b1111111111111111 8
b11111111111111110 <
b1 ;
14
11
12
b11 -
bx ,
b10 0
b1011010000000001 (
b110111 .
1!
#10
b100 &
b100 >
b100 ;
b11111111111111011 <
b1111111111111100 8
b10 /
b11 *
b11 7
bx +
b1 '
b1 5
1"
#11
0!
#12
0"
#13
0?
b100 &
b100 >
b0 %
0=
b100 <
b1 6
b11 8
b100 ;
09
03
04
02
bx (
b10 .
b100 -
b11 0
1!
#14
bx &
bx >
x?
bx %
x=
bx ;
bx <
b100 6
bx 8
b100 '
b100 5
b110000 /
bx *
bx 7
1"
#15
0!
#16
0"
#17
bx &
bx >
b0x %
0=
b1111111111111111 6
b0xxxxxxxxxxxxxxxx ;
b0xxxxxxxxxxxxxxxx <
19
13
01
b101 -
b100 0
b110000 .
1!
#18
bx '
bx 5
1"
